utils_gao/__init__.py
utils_gao/plotting.py
utils_gao/utils_gao.py
utils_gao-0.1.0.dist-info/DESCRIPTION.rst
utils_gao-0.1.0.dist-info/METADATA
utils_gao-0.1.0.dist-info/RECORD
utils_gao-0.1.0.dist-info/WHEEL
utils_gao-0.1.0.dist-info/metadata.json
utils_gao-0.1.0.dist-info/top_level.txt
