Metadata-Version: 2.0
Name: utils-gao
Version: 0.1.0
Summary: utils module for my ML
Home-page: https://github.com/pjgao
Author: pipixiu
Author-email: 1783198484@qq.com
License: UNKNOWN
Platform: UNKNOWN
Classifier: Programming Language :: Python :: 3
Classifier: License :: OSI Approved :: MIT License
Classifier: Operating System :: OS Independent
